{
  "accounts": [
    {
      "name": "Cuenta CI",
      "suspended": false,
      "email": "optional_if_using_cookies@example.com",
      "password": "optional_if_using_cookies",
      "locale": "es-ES",
      "default_message": "Hola, este post se ejecuta desde GitHub Actions headless.",
      "default_images": [
        "assets/example-image.jpg"
      ],
      "groups": [
        {
          "id": "123456789012345"
        },
        {
          "id": "987654321098765",
          "message": "Mensaje especifico para este grupo",
          "images": [
            "assets/another-image.jpg"
          ]
        }
      ]
    }
  ]
}
